{
  "schemaVersion": "ReadingExamDocumentV1",
  "examId": "p1-low-11",
  "meta": {
    "title": "Bovids",
    "category": "P1",
    "frequency": "low",
    "pdfFilename": "108. P1 - Bovids 牛科动物.pdf",
    "legacyPath": "睡着过项目组/2. 所有文章(11.20)[192篇]/108. P1 - Bovids 牛科动物/",
    "legacyFilename": "108. P1 - Bovids 牛科动物.html",
    "questionIntroHtml": "<h3>Questions</h3>",
    "originalTitle": "Bovids 牛科动物"
  },
  "explanationKey": null,
  "passageBlocks": [
    {
      "blockId": "passage-main",
      "kind": "html",
      "nodes": [
        {
          "type": "element",
          "tag": "h2",
          "attrs": {},
          "children": [
            {
              "type": "text",
              "text": "Bovids"
            }
          ]
        },
        {
          "type": "text",
          "text": "\n            \n            "
        },
        {
          "type": "element",
          "tag": "p",
          "attrs": {},
          "children": [
            {
              "type": "text",
              "text": "The family of mammals called bovids belongs to the Artiodactyl class, which also includes giraffes. Bovids are a highly diverse group consisting of 137 species, some of which are man's most important domestic animals."
            }
          ]
        },
        {
          "type": "text",
          "text": "\n            "
        },
        {
          "type": "element",
          "tag": "p",
          "attrs": {},
          "children": [
            {
              "type": "text",
              "text": "Bovids are well represented in most parts of Eurasia and Southeast Asian islands, but they are by far the most numerous and diverse in the latter. Some species of bovid are solitary, but others live in large groups with complex social structures. Although bovids have adapted to a wide range of habitats, from arctic tundra to deep tropical forest, the majority of species favour open grassland, scrub or desert. This diversity of habitat is also matched by great diversity in size and form: at one extreme is the royal antelope of West Africa, which stands a mere 25 cm at the shoulder; at the other, the massively built bison of North America and Europe, growing to a shoulder height of 2.2m."
            }
          ]
        },
        {
          "type": "text",
          "text": "\n            "
        },
        {
          "type": "element",
          "tag": "p",
          "attrs": {},
          "children": [
            {
              "type": "text",
              "text": "Despite differences in size and appearance, bovids are united by the possession of certain common features. All species are ruminants, which means that they retain undigested food in their stomachs, and regurgitate it as necessary. Bovids are almost exclusively herbivorous. Typically, their teeth are highly modified for browsing and grazing: grass or foliage is cropped with the upper lip and lower incisors (the upper incisors are usually absent), and then ground down by the cheek teeth. As well as having cloven, or split hooves, the males of all bovid species and the females of most carry horns. Bovid horns have bony cores covered in a sheath of horny material that is constantly renewed from within; they are unbranched and never shed. They vary in shape and size: the relatively simple horns of a large Indian buffalo may measure around 4 m from tip to tip along the outer curve, while the various gazelles have horns with a variety of elegant curves."
            }
          ]
        },
        {
          "type": "text",
          "text": "\n            "
        },
        {
          "type": "element",
          "tag": "p",
          "attrs": {},
          "children": [
            {
              "type": "text",
              "text": "Five groups, or sub-families, may be distinguished: Bovinae, Antelope, Caprinae, Cephalophinae and Antilocapridae. The sub-family Bovinae comprises most of the larger bovids, including the African bongo, nilgai, eland, bison and cattle. Unlike most other bovids, they are all non-territorial. The ancestors of the various species of domestic cattle (such as banteng, gaur, yak and water buffalo) are generally rare and endangered in the wild, while the auroch (the ancestor of the domestic cattle of Europe) is extinct."
            }
          ]
        },
        {
          "type": "text",
          "text": "\n            "
        },
        {
          "type": "element",
          "tag": "p",
          "attrs": {},
          "children": [
            {
              "type": "text",
              "text": "The term 'antelope' is not a very precise zoological name – it is used to loosely describe a number of bovids that have followed different lines of development. Antelopes are typically long-legged, fast-running species, often with long horns that may be laid along the back when the animal is in full flight. There are two main sub-groups of antelope: Hippotraginae, which includes the oryx and the addax, and Antilopinae, which generally contains slighter and more graceful animals such as gazelle and the springbok. Antelopes are mainly grassland species, but many have adapted to flooded grasslands: pukus, waterbucks and lechwes are all good at swimming, usually feeding in deep water, while the sitatunga has long, splayed hooves that enable it to walk freely on swampy ground."
            }
          ]
        },
        {
          "type": "text",
          "text": "\n            "
        },
        {
          "type": "element",
          "tag": "p",
          "attrs": {},
          "children": [
            {
              "type": "text",
              "text": "The sub-family Caprinae includes the sheep and the goat, together with various relatives such as the goral and the tahr. Most are woolly or have long hair. Several species, such as wild goats, chamois and ibex, are agile cliff and mountain-dwellers. Tolerance of extreme conditions is most marked in this group: barbary and bighorn sheep have adapted to arid deserts, while Rocky Mountain sheep survive high up in mountains and musk oxen in arctic tundra."
            }
          ]
        },
        {
          "type": "text",
          "text": "\n            "
        },
        {
          "type": "element",
          "tag": "p",
          "attrs": {},
          "children": [
            {
              "type": "text",
              "text": "The duiker of Africa belongs to the Cephalophinae sub-family. It is generally small and solitary, often living in thick forest. Although mainly feeding on grass and leaves, some duikers - unlike most other bovids – are believed to eat insects and feed on dead animal carcasses, and even to kill small animals."
            }
          ]
        },
        {
          "type": "text",
          "text": "\n            "
        },
        {
          "type": "element",
          "tag": "p",
          "attrs": {},
          "children": [
            {
              "type": "text",
              "text": "The pronghorn is the sole survivor of a New World sub-family of herbivorous ruminants, the Antilocapridae in North America. It is similar in appearance and habits to the Old World antelope. Although greatly reduced in numbers since the arrival of Europeans, and the subsequent enclosure of grasslands, the pronghorn is still found in considerable numbers throughout North America, from Washington State to Mexico. When alarmed by the approach of wolves or other predators, hairs on the pronghorn's rump stand erect, so showing and emphasising the white patch there. At this signal, the whole herd gallops off at speed of over 60 km per hour."
            }
          ]
        },
        {
          "type": "text",
          "text": "\n            "
        },
        {
          "type": "element",
          "tag": "div",
          "attrs": {
            "class": "empty-space"
          },
          "children": []
        },
        {
          "type": "text",
          "text": "\n        "
        },
        {
          "type": "text",
          "text": "\n        \n        "
        },
        {
          "type": "element",
          "tag": "div",
          "attrs": {
            "id": "divider"
          },
          "children": []
        }
      ]
    }
  ],
  "questionGroups": [
    {
      "groupId": "group-1",
      "kind": "single_choice",
      "questionIds": [
        "q1",
        "q2",
        "q3"
      ],
      "allowOptionReuse": false,
      "leadNodes": [
        {
          "type": "element",
          "tag": "h3",
          "attrs": {},
          "children": [
            {
              "type": "text",
              "text": "Questions"
            }
          ]
        }
      ],
      "contentNodes": [
        {
          "type": "element",
          "tag": "div",
          "attrs": {
            "class": "group",
            "id": "q1-2-3-anchor"
          },
          "children": [
            {
              "type": "text",
              "text": "\n                "
            },
            {
              "type": "element",
              "tag": "h4",
              "attrs": {},
              "children": [
                {
                  "type": "text",
                  "text": "Questions 1–3"
                }
              ]
            },
            {
              "type": "text",
              "text": "\n                "
            },
            {
              "type": "element",
              "tag": "p",
              "attrs": {},
              "children": [
                {
                  "type": "text",
                  "text": "Choose the correct letter, "
                },
                {
                  "type": "element",
                  "tag": "strong",
                  "attrs": {},
                  "children": [
                    {
                      "type": "text",
                      "text": "A, B, C"
                    }
                  ]
                },
                {
                  "type": "text",
                  "text": " or "
                },
                {
                  "type": "element",
                  "tag": "strong",
                  "attrs": {},
                  "children": [
                    {
                      "type": "text",
                      "text": "D"
                    }
                  ]
                },
                {
                  "type": "text",
                  "text": "."
                }
              ]
            },
            {
              "type": "text",
              "text": "\n                \n                "
            },
            {
              "type": "element",
              "tag": "div",
              "attrs": {
                "class": "question-item"
              },
              "children": [
                {
                  "type": "text",
                  "text": "\n                    "
                },
                {
                  "type": "element",
                  "tag": "p",
                  "attrs": {},
                  "children": [
                    {
                      "type": "element",
                      "tag": "strong",
                      "attrs": {},
                      "children": [
                        {
                          "type": "text",
                          "text": "1"
                        }
                      ]
                    },
                    {
                      "type": "text",
                      "text": " In which region is the biggest range of bovids to be found?"
                    }
                  ]
                },
                {
                  "type": "text",
                  "text": "\n                    "
                },
                {
                  "type": "element",
                  "tag": "div",
                  "attrs": {
                    "class": "radio-options"
                  },
                  "children": [
                    {
                      "type": "text",
                      "text": "\n                        "
                    },
                    {
                      "type": "element",
                      "tag": "label",
                      "attrs": {},
                      "children": [
                        {
                          "type": "choiceInput",
                          "inputType": "radio",
                          "fieldName": "q1",
                          "questionId": "q1",
                          "questionIds": [
                            "q1"
                          ],
                          "value": "A",
                          "attrs": {
                            "name": "q1",
                            "type": "radio",
                            "value": "A"
                          }
                        },
                        {
                          "type": "text",
                          "text": " A Africa"
                        }
                      ]
                    },
                    {
                      "type": "text",
                      "text": "\n                        "
                    },
                    {
                      "type": "element",
                      "tag": "label",
                      "attrs": {},
                      "children": [
                        {
                          "type": "choiceInput",
                          "inputType": "radio",
                          "fieldName": "q1",
                          "questionId": "q1",
                          "questionIds": [
                            "q1"
                          ],
                          "value": "B",
                          "attrs": {
                            "name": "q1",
                            "type": "radio",
                            "value": "B"
                          }
                        },
                        {
                          "type": "text",
                          "text": " B Eurasia"
                        }
                      ]
                    },
                    {
                      "type": "text",
                      "text": "\n                        "
                    },
                    {
                      "type": "element",
                      "tag": "label",
                      "attrs": {},
                      "children": [
                        {
                          "type": "choiceInput",
                          "inputType": "radio",
                          "fieldName": "q1",
                          "questionId": "q1",
                          "questionIds": [
                            "q1"
                          ],
                          "value": "C",
                          "attrs": {
                            "name": "q1",
                            "type": "radio",
                            "value": "C"
                          }
                        },
                        {
                          "type": "text",
                          "text": " C North America"
                        }
                      ]
                    },
                    {
                      "type": "text",
                      "text": "\n                        "
                    },
                    {
                      "type": "element",
                      "tag": "label",
                      "attrs": {},
                      "children": [
                        {
                          "type": "choiceInput",
                          "inputType": "radio",
                          "fieldName": "q1",
                          "questionId": "q1",
                          "questionIds": [
                            "q1"
                          ],
                          "value": "D",
                          "attrs": {
                            "name": "q1",
                            "type": "radio",
                            "value": "D"
                          }
                        },
                        {
                          "type": "text",
                          "text": " D South-east Asia"
                        }
                      ]
                    },
                    {
                      "type": "text",
                      "text": "\n                    "
                    }
                  ]
                },
                {
                  "type": "text",
                  "text": "\n                "
                }
              ]
            },
            {
              "type": "text",
              "text": "\n                "
            },
            {
              "type": "element",
              "tag": "div",
              "attrs": {
                "class": "question-item"
              },
              "children": [
                {
                  "type": "text",
                  "text": "\n                    "
                },
                {
                  "type": "element",
                  "tag": "p",
                  "attrs": {},
                  "children": [
                    {
                      "type": "element",
                      "tag": "strong",
                      "attrs": {},
                      "children": [
                        {
                          "type": "text",
                          "text": "2"
                        }
                      ]
                    },
                    {
                      "type": "text",
                      "text": " Most bovids have a preference for living in"
                    }
                  ]
                },
                {
                  "type": "text",
                  "text": "\n                    "
                },
                {
                  "type": "element",
                  "tag": "div",
                  "attrs": {
                    "class": "radio-options"
                  },
                  "children": [
                    {
                      "type": "text",
                      "text": "\n                        "
                    },
                    {
                      "type": "element",
                      "tag": "label",
                      "attrs": {},
                      "children": [
                        {
                          "type": "choiceInput",
                          "inputType": "radio",
                          "fieldName": "q2",
                          "questionId": "q2",
                          "questionIds": [
                            "q2"
                          ],
                          "value": "A",
                          "attrs": {
                            "name": "q2",
                            "type": "radio",
                            "value": "A"
                          }
                        },
                        {
                          "type": "text",
                          "text": " A isolation."
                        }
                      ]
                    },
                    {
                      "type": "text",
                      "text": "\n                        "
                    },
                    {
                      "type": "element",
                      "tag": "label",
                      "attrs": {},
                      "children": [
                        {
                          "type": "choiceInput",
                          "inputType": "radio",
                          "fieldName": "q2",
                          "questionId": "q2",
                          "questionIds": [
                            "q2"
                          ],
                          "value": "B",
                          "attrs": {
                            "name": "q2",
                            "type": "radio",
                            "value": "B"
                          }
                        },
                        {
                          "type": "text",
                          "text": " B small groups."
                        }
                      ]
                    },
                    {
                      "type": "text",
                      "text": "\n                        "
                    },
                    {
                      "type": "element",
                      "tag": "label",
                      "attrs": {},
                      "children": [
                        {
                          "type": "choiceInput",
                          "inputType": "radio",
                          "fieldName": "q2",
                          "questionId": "q2",
                          "questionIds": [
                            "q2"
                          ],
                          "value": "C",
                          "attrs": {
                            "name": "q2",
                            "type": "radio",
                            "value": "C"
                          }
                        },
                        {
                          "type": "text",
                          "text": " C tropical forest."
                        }
                      ]
                    },
                    {
                      "type": "text",
                      "text": "\n                        "
                    },
                    {
                      "type": "element",
                      "tag": "label",
                      "attrs": {},
                      "children": [
                        {
                          "type": "choiceInput",
                          "inputType": "radio",
                          "fieldName": "q2",
                          "questionId": "q2",
                          "questionIds": [
                            "q2"
                          ],
                          "value": "D",
                          "attrs": {
                            "name": "q2",
                            "type": "radio",
                            "value": "D"
                          }
                        },
                        {
                          "type": "text",
                          "text": " D wide open spaces."
                        }
                      ]
                    },
                    {
                      "type": "text",
                      "text": "\n                    "
                    }
                  ]
                },
                {
                  "type": "text",
                  "text": "\n                "
                }
              ]
            },
            {
              "type": "text",
              "text": "\n                "
            },
            {
              "type": "element",
              "tag": "div",
              "attrs": {
                "class": "question-item"
              },
              "children": [
                {
                  "type": "text",
                  "text": "\n                    "
                },
                {
                  "type": "element",
                  "tag": "p",
                  "attrs": {},
                  "children": [
                    {
                      "type": "element",
                      "tag": "strong",
                      "attrs": {},
                      "children": [
                        {
                          "type": "text",
                          "text": "3"
                        }
                      ]
                    },
                    {
                      "type": "text",
                      "text": " Which of the following features do all bovids have in common?"
                    }
                  ]
                },
                {
                  "type": "text",
                  "text": "\n                    "
                },
                {
                  "type": "element",
                  "tag": "div",
                  "attrs": {
                    "class": "radio-options"
                  },
                  "children": [
                    {
                      "type": "text",
                      "text": "\n                        "
                    },
                    {
                      "type": "element",
                      "tag": "label",
                      "attrs": {},
                      "children": [
                        {
                          "type": "choiceInput",
                          "inputType": "radio",
                          "fieldName": "q3",
                          "questionId": "q3",
                          "questionIds": [
                            "q3"
                          ],
                          "value": "A",
                          "attrs": {
                            "name": "q3",
                            "type": "radio",
                            "value": "A"
                          }
                        },
                        {
                          "type": "text",
                          "text": " A Their horns are shed"
                        }
                      ]
                    },
                    {
                      "type": "text",
                      "text": "\n                        "
                    },
                    {
                      "type": "element",
                      "tag": "label",
                      "attrs": {},
                      "children": [
                        {
                          "type": "choiceInput",
                          "inputType": "radio",
                          "fieldName": "q3",
                          "questionId": "q3",
                          "questionIds": [
                            "q3"
                          ],
                          "value": "B",
                          "attrs": {
                            "name": "q3",
                            "type": "radio",
                            "value": "B"
                          }
                        },
                        {
                          "type": "text",
                          "text": " B They have upper incisors"
                        }
                      ]
                    },
                    {
                      "type": "text",
                      "text": "\n                        "
                    },
                    {
                      "type": "element",
                      "tag": "label",
                      "attrs": {},
                      "children": [
                        {
                          "type": "choiceInput",
                          "inputType": "radio",
                          "fieldName": "q3",
                          "questionId": "q3",
                          "questionIds": [
                            "q3"
                          ],
                          "value": "C",
                          "attrs": {
                            "name": "q3",
                            "type": "radio",
                            "value": "C"
                          }
                        },
                        {
                          "type": "text",
                          "text": " C They store food in the body"
                        }
                      ]
                    },
                    {
                      "type": "text",
                      "text": "\n                        "
                    },
                    {
                      "type": "element",
                      "tag": "label",
                      "attrs": {},
                      "children": [
                        {
                          "type": "choiceInput",
                          "inputType": "radio",
                          "fieldName": "q3",
                          "questionId": "q3",
                          "questionIds": [
                            "q3"
                          ],
                          "value": "D",
                          "attrs": {
                            "name": "q3",
                            "type": "radio",
                            "value": "D"
                          }
                        },
                        {
                          "type": "text",
                          "text": " D Their hooves are undivided"
                        }
                      ]
                    },
                    {
                      "type": "text",
                      "text": "\n                    "
                    }
                  ]
                },
                {
                  "type": "text",
                  "text": "\n                "
                }
              ]
            },
            {
              "type": "text",
              "text": "\n            "
            }
          ]
        }
      ],
      "explanationSection": null
    },
    {
      "groupId": "group-2",
      "kind": "matching",
      "questionIds": [
        "q4",
        "q5",
        "q6",
        "q7",
        "q8"
      ],
      "allowOptionReuse": true,
      "leadNodes": [],
      "contentNodes": [
        {
          "type": "element",
          "tag": "div",
          "attrs": {
            "class": "group",
            "id": "q4-5-6-7-8-anchor"
          },
          "children": [
            {
              "type": "text",
              "text": "\n                "
            },
            {
              "type": "element",
              "tag": "h4",
              "attrs": {},
              "children": [
                {
                  "type": "text",
                  "text": "Questions 4–8"
                }
              ]
            },
            {
              "type": "text",
              "text": "\n                "
            },
            {
              "type": "element",
              "tag": "p",
              "attrs": {},
              "children": [
                {
                  "type": "text",
                  "text": "Look at the following characteristics and the list of sub-families below."
                }
              ]
            },
            {
              "type": "text",
              "text": "\n                "
            },
            {
              "type": "element",
              "tag": "p",
              "attrs": {},
              "children": [
                {
                  "type": "text",
                  "text": "Match each characteristic with the correct sub-family, "
                },
                {
                  "type": "element",
                  "tag": "strong",
                  "attrs": {},
                  "children": [
                    {
                      "type": "text",
                      "text": "A, B, C"
                    }
                  ]
                },
                {
                  "type": "text",
                  "text": " or "
                },
                {
                  "type": "element",
                  "tag": "strong",
                  "attrs": {},
                  "children": [
                    {
                      "type": "text",
                      "text": "D"
                    }
                  ]
                },
                {
                  "type": "text",
                  "text": "."
                }
              ]
            },
            {
              "type": "text",
              "text": "\n                "
            },
            {
              "type": "element",
              "tag": "p",
              "attrs": {},
              "children": [
                {
                  "type": "element",
                  "tag": "em",
                  "attrs": {},
                  "children": [
                    {
                      "type": "text",
                      "text": "NB You may use any letter more than once."
                    }
                  ]
                }
              ]
            },
            {
              "type": "text",
              "text": "\n                \n                "
            },
            {
              "type": "element",
              "tag": "div",
              "attrs": {
                "class": "match-question-item"
              },
              "children": [
                {
                  "type": "text",
                  "text": "\n                    "
                },
                {
                  "type": "element",
                  "tag": "p",
                  "attrs": {},
                  "children": [
                    {
                      "type": "element",
                      "tag": "strong",
                      "attrs": {},
                      "children": [
                        {
                          "type": "text",
                          "text": "4"
                        }
                      ]
                    },
                    {
                      "type": "text",
                      "text": " can endure very harsh environments"
                    }
                  ]
                },
                {
                  "type": "text",
                  "text": "\n                    "
                },
                {
                  "type": "dropzone",
                  "appearance": "match",
                  "questionId": "q4",
                  "paragraph": "",
                  "labelText": "",
                  "attrs": {
                    "class": "match-dropzone",
                    "data-question": "q4"
                  }
                },
                {
                  "type": "text",
                  "text": "\n                "
                }
              ]
            },
            {
              "type": "text",
              "text": "\n                "
            },
            {
              "type": "element",
              "tag": "div",
              "attrs": {
                "class": "match-question-item"
              },
              "children": [
                {
                  "type": "text",
                  "text": "\n                    "
                },
                {
                  "type": "element",
                  "tag": "p",
                  "attrs": {},
                  "children": [
                    {
                      "type": "element",
                      "tag": "strong",
                      "attrs": {},
                      "children": [
                        {
                          "type": "text",
                          "text": "5"
                        }
                      ]
                    },
                    {
                      "type": "text",
                      "text": " includes the ox and the cow"
                    }
                  ]
                },
                {
                  "type": "text",
                  "text": "\n                    "
                },
                {
                  "type": "dropzone",
                  "appearance": "match",
                  "questionId": "q5",
                  "paragraph": "",
                  "labelText": "",
                  "attrs": {
                    "class": "match-dropzone",
                    "data-question": "q5"
                  }
                },
                {
                  "type": "text",
                  "text": "\n                "
                }
              ]
            },
            {
              "type": "text",
              "text": "\n                "
            },
            {
              "type": "element",
              "tag": "div",
              "attrs": {
                "class": "match-question-item"
              },
              "children": [
                {
                  "type": "text",
                  "text": "\n                    "
                },
                {
                  "type": "element",
                  "tag": "p",
                  "attrs": {},
                  "children": [
                    {
                      "type": "element",
                      "tag": "strong",
                      "attrs": {},
                      "children": [
                        {
                          "type": "text",
                          "text": "6"
                        }
                      ]
                    },
                    {
                      "type": "text",
                      "text": " may supplement its diet with meat"
                    }
                  ]
                },
                {
                  "type": "text",
                  "text": "\n                    "
                },
                {
                  "type": "dropzone",
                  "appearance": "match",
                  "questionId": "q6",
                  "paragraph": "",
                  "labelText": "",
                  "attrs": {
                    "class": "match-dropzone",
                    "data-question": "q6"
                  }
                },
                {
                  "type": "text",
                  "text": "\n                "
                }
              ]
            },
            {
              "type": "text",
              "text": "\n                "
            },
            {
              "type": "element",
              "tag": "div",
              "attrs": {
                "class": "match-question-item"
              },
              "children": [
                {
                  "type": "text",
                  "text": "\n                    "
                },
                {
                  "type": "element",
                  "tag": "p",
                  "attrs": {},
                  "children": [
                    {
                      "type": "element",
                      "tag": "strong",
                      "attrs": {},
                      "children": [
                        {
                          "type": "text",
                          "text": "7"
                        }
                      ]
                    },
                    {
                      "type": "text",
                      "text": " can usually move at speed"
                    }
                  ]
                },
                {
                  "type": "text",
                  "text": "\n                    "
                },
                {
                  "type": "dropzone",
                  "appearance": "match",
                  "questionId": "q7",
                  "paragraph": "",
                  "labelText": "",
                  "attrs": {
                    "class": "match-dropzone",
                    "data-question": "q7"
                  }
                },
                {
                  "type": "text",
                  "text": "\n                "
                }
              ]
            },
            {
              "type": "text",
              "text": "\n                "
            },
            {
              "type": "element",
              "tag": "div",
              "attrs": {
                "class": "match-question-item"
              },
              "children": [
                {
                  "type": "text",
                  "text": "\n                    "
                },
                {
                  "type": "element",
                  "tag": "p",
                  "attrs": {},
                  "children": [
                    {
                      "type": "element",
                      "tag": "strong",
                      "attrs": {},
                      "children": [
                        {
                          "type": "text",
                          "text": "8"
                        }
                      ]
                    },
                    {
                      "type": "text",
                      "text": " does not defend a particular area of land"
                    }
                  ]
                },
                {
                  "type": "text",
                  "text": "\n                    "
                },
                {
                  "type": "dropzone",
                  "appearance": "match",
                  "questionId": "q8",
                  "paragraph": "",
                  "labelText": "",
                  "attrs": {
                    "class": "match-dropzone",
                    "data-question": "q8"
                  }
                },
                {
                  "type": "text",
                  "text": "\n                "
                }
              ]
            },
            {
              "type": "text",
              "text": "\n\n                "
            },
            {
              "type": "element",
              "tag": "div",
              "attrs": {
                "class": "options-pool",
                "id": "subfamily-options-pool"
              },
              "children": [
                {
                  "type": "text",
                  "text": "\n                    "
                },
                {
                  "type": "element",
                  "tag": "strong",
                  "attrs": {},
                  "children": [
                    {
                      "type": "text",
                      "text": "List of sub-families"
                    }
                  ]
                },
                {
                  "type": "text",
                  "text": "\n                    "
                },
                {
                  "type": "element",
                  "tag": "div",
                  "attrs": {
                    "class": "pool-items",
                    "id": "practice-pool-1"
                  },
                  "children": [
                    {
                      "type": "text",
                      "text": "\n                        "
                    },
                    {
                      "type": "optionChip",
                      "poolId": "practice-pool-1",
                      "value": "A",
                      "label": "A Antelope",
                      "attrs": {
                        "class": "drag-item",
                        "id": "subfam-A",
                        "data-option": "A"
                      }
                    },
                    {
                      "type": "text",
                      "text": "\n                        "
                    },
                    {
                      "type": "optionChip",
                      "poolId": "practice-pool-1",
                      "value": "B",
                      "label": "B Bovinae",
                      "attrs": {
                        "class": "drag-item",
                        "id": "subfam-B",
                        "data-option": "B"
                      }
                    },
                    {
                      "type": "text",
                      "text": "\n                        "
                    },
                    {
                      "type": "optionChip",
                      "poolId": "practice-pool-1",
                      "value": "C",
                      "label": "C Caprinae",
                      "attrs": {
                        "class": "drag-item",
                        "id": "subfam-C",
                        "data-option": "C"
                      }
                    },
                    {
                      "type": "text",
                      "text": "\n                        "
                    },
                    {
                      "type": "optionChip",
                      "poolId": "practice-pool-1",
                      "value": "D",
                      "label": "D Cephalophinae",
                      "attrs": {
                        "class": "drag-item",
                        "id": "subfam-D",
                        "data-option": "D"
                      }
                    },
                    {
                      "type": "text",
                      "text": "\n                    "
                    }
                  ]
                },
                {
                  "type": "text",
                  "text": "\n                "
                }
              ]
            },
            {
              "type": "text",
              "text": "\n            "
            }
          ]
        }
      ],
      "explanationSection": null
    },
    {
      "groupId": "group-3",
      "kind": "sentence_completion",
      "questionIds": [
        "q9",
        "q10",
        "q11",
        "q12",
        "q13"
      ],
      "allowOptionReuse": false,
      "leadNodes": [],
      "contentNodes": [
        {
          "type": "element",
          "tag": "div",
          "attrs": {
            "class": "group",
            "id": "q9-10-11-12-13-anchor"
          },
          "children": [
            {
              "type": "text",
              "text": "\n                "
            },
            {
              "type": "element",
              "tag": "h4",
              "attrs": {},
              "children": [
                {
                  "type": "text",
                  "text": "Questions 9–13"
                }
              ]
            },
            {
              "type": "text",
              "text": "\n                "
            },
            {
              "type": "element",
              "tag": "p",
              "attrs": {},
              "children": [
                {
                  "type": "text",
                  "text": "Answer the questions below."
                }
              ]
            },
            {
              "type": "text",
              "text": "\n                "
            },
            {
              "type": "element",
              "tag": "p",
              "attrs": {},
              "children": [
                {
                  "type": "text",
                  "text": "Choose "
                },
                {
                  "type": "element",
                  "tag": "strong",
                  "attrs": {},
                  "children": [
                    {
                      "type": "text",
                      "text": "NO MORE THAN THREE WORDS"
                    }
                  ]
                },
                {
                  "type": "text",
                  "text": " from the passage for each answer."
                }
              ]
            },
            {
              "type": "text",
              "text": "\n                \n                "
            },
            {
              "type": "element",
              "tag": "ul",
              "attrs": {
                "class": "short-answer-list"
              },
              "children": [
                {
                  "type": "text",
                  "text": "\n                    "
                },
                {
                  "type": "element",
                  "tag": "li",
                  "attrs": {
                    "class": "short-answer-item"
                  },
                  "children": [
                    {
                      "type": "text",
                      "text": "\n                        "
                    },
                    {
                      "type": "element",
                      "tag": "p",
                      "attrs": {},
                      "children": [
                        {
                          "type": "element",
                          "tag": "strong",
                          "attrs": {},
                          "children": [
                            {
                              "type": "text",
                              "text": "9"
                            }
                          ]
                        },
                        {
                          "type": "text",
                          "text": " What is the smallest species of Bovid called?"
                        }
                      ]
                    },
                    {
                      "type": "text",
                      "text": "\n                        "
                    },
                    {
                      "type": "textInput",
                      "questionId": "q9",
                      "fieldName": "q9",
                      "attrs": {
                        "name": "q9",
                        "type": "text",
                        "id": "q9_input"
                      }
                    },
                    {
                      "type": "text",
                      "text": "\n                    "
                    }
                  ]
                },
                {
                  "type": "text",
                  "text": "\n                    "
                },
                {
                  "type": "element",
                  "tag": "li",
                  "attrs": {
                    "class": "short-answer-item"
                  },
                  "children": [
                    {
                      "type": "text",
                      "text": "\n                        "
                    },
                    {
                      "type": "element",
                      "tag": "p",
                      "attrs": {},
                      "children": [
                        {
                          "type": "element",
                          "tag": "strong",
                          "attrs": {},
                          "children": [
                            {
                              "type": "text",
                              "text": "10"
                            }
                          ]
                        },
                        {
                          "type": "text",
                          "text": " Which species of Bovinae has now died out?"
                        }
                      ]
                    },
                    {
                      "type": "text",
                      "text": "\n                        "
                    },
                    {
                      "type": "textInput",
                      "questionId": "q10",
                      "fieldName": "q10",
                      "attrs": {
                        "name": "q10",
                        "type": "text",
                        "id": "q10_input"
                      }
                    },
                    {
                      "type": "text",
                      "text": "\n                    "
                    }
                  ]
                },
                {
                  "type": "text",
                  "text": "\n                    "
                },
                {
                  "type": "element",
                  "tag": "li",
                  "attrs": {
                    "class": "short-answer-item"
                  },
                  "children": [
                    {
                      "type": "text",
                      "text": "\n                        "
                    },
                    {
                      "type": "element",
                      "tag": "p",
                      "attrs": {},
                      "children": [
                        {
                          "type": "element",
                          "tag": "strong",
                          "attrs": {},
                          "children": [
                            {
                              "type": "text",
                              "text": "11"
                            }
                          ]
                        },
                        {
                          "type": "text",
                          "text": " What facilitates the movement of the sitatunga over wetland?"
                        }
                      ]
                    },
                    {
                      "type": "text",
                      "text": "\n                        "
                    },
                    {
                      "type": "textInput",
                      "questionId": "q11",
                      "fieldName": "q11",
                      "attrs": {
                        "name": "q11",
                        "type": "text",
                        "id": "q11_input"
                      }
                    },
                    {
                      "type": "text",
                      "text": "\n                    "
                    }
                  ]
                },
                {
                  "type": "text",
                  "text": "\n                    "
                },
                {
                  "type": "element",
                  "tag": "li",
                  "attrs": {
                    "class": "short-answer-item"
                  },
                  "children": [
                    {
                      "type": "text",
                      "text": "\n                        "
                    },
                    {
                      "type": "element",
                      "tag": "p",
                      "attrs": {},
                      "children": [
                        {
                          "type": "element",
                          "tag": "strong",
                          "attrs": {},
                          "children": [
                            {
                              "type": "text",
                              "text": "12"
                            }
                          ]
                        },
                        {
                          "type": "text",
                          "text": " What sort of terrain do barbary sheep live in?"
                        }
                      ]
                    },
                    {
                      "type": "text",
                      "text": "\n                        "
                    },
                    {
                      "type": "textInput",
                      "questionId": "q12",
                      "fieldName": "q12",
                      "attrs": {
                        "name": "q12",
                        "type": "text",
                        "id": "q12_input"
                      }
                    },
                    {
                      "type": "text",
                      "text": "\n                    "
                    }
                  ]
                },
                {
                  "type": "text",
                  "text": "\n                    "
                },
                {
                  "type": "element",
                  "tag": "li",
                  "attrs": {
                    "class": "short-answer-item"
                  },
                  "children": [
                    {
                      "type": "text",
                      "text": "\n                        "
                    },
                    {
                      "type": "element",
                      "tag": "p",
                      "attrs": {},
                      "children": [
                        {
                          "type": "element",
                          "tag": "strong",
                          "attrs": {},
                          "children": [
                            {
                              "type": "text",
                              "text": "13"
                            }
                          ]
                        },
                        {
                          "type": "text",
                          "text": " What is the only living member of the Antilocapridae sub-family?"
                        }
                      ]
                    },
                    {
                      "type": "text",
                      "text": "\n                        "
                    },
                    {
                      "type": "textInput",
                      "questionId": "q13",
                      "fieldName": "q13",
                      "attrs": {
                        "name": "q13",
                        "type": "text",
                        "id": "q13_input"
                      }
                    },
                    {
                      "type": "text",
                      "text": "\n                    "
                    }
                  ]
                },
                {
                  "type": "text",
                  "text": "\n                "
                }
              ]
            },
            {
              "type": "text",
              "text": "\n            "
            }
          ]
        }
      ],
      "explanationSection": null
    }
  ],
  "questionItems": [
    {
      "questionId": "q1",
      "displayNumber": "1",
      "anchorId": "q1-2-3-anchor"
    },
    {
      "questionId": "q2",
      "displayNumber": "2",
      "anchorId": "q2_input"
    },
    {
      "questionId": "q3",
      "displayNumber": "3",
      "anchorId": "q3_input"
    },
    {
      "questionId": "q4",
      "displayNumber": "4",
      "anchorId": "q4-5-6-7-8-anchor"
    },
    {
      "questionId": "q5",
      "displayNumber": "5",
      "anchorId": "q5"
    },
    {
      "questionId": "q6",
      "displayNumber": "6",
      "anchorId": "q6"
    },
    {
      "questionId": "q7",
      "displayNumber": "7",
      "anchorId": "q7"
    },
    {
      "questionId": "q8",
      "displayNumber": "8",
      "anchorId": "q8"
    },
    {
      "questionId": "q9",
      "displayNumber": "9",
      "anchorId": "q9-10-11-12-13-anchor"
    },
    {
      "questionId": "q10",
      "displayNumber": "10",
      "anchorId": "q10_input"
    },
    {
      "questionId": "q11",
      "displayNumber": "11",
      "anchorId": "q11_input"
    },
    {
      "questionId": "q12",
      "displayNumber": "12",
      "anchorId": "q12_input"
    },
    {
      "questionId": "q13",
      "displayNumber": "13",
      "anchorId": "q13_input"
    }
  ],
  "options": [
    {
      "poolId": "practice-pool-1",
      "value": "A",
      "label": "A Antelope"
    },
    {
      "poolId": "practice-pool-1",
      "value": "B",
      "label": "B Bovinae"
    },
    {
      "poolId": "practice-pool-1",
      "value": "C",
      "label": "C Caprinae"
    },
    {
      "poolId": "practice-pool-1",
      "value": "D",
      "label": "D Cephalophinae"
    }
  ],
  "answerKey": {
    "q1": "D",
    "q2": "D",
    "q3": "C",
    "q4": "C",
    "q5": "B",
    "q6": "D",
    "q7": "A",
    "q8": "B",
    "q9": "royal antelope",
    "q10": "auroch",
    "q11": "splayed hooves",
    "q12": "arid deserts",
    "q13": "pronghorn"
  },
  "questionOrder": [
    "q1",
    "q2",
    "q3",
    "q4",
    "q5",
    "q6",
    "q7",
    "q8",
    "q9",
    "q10",
    "q11",
    "q12",
    "q13"
  ],
  "questionDisplayMap": {
    "q1": "1",
    "q2": "2",
    "q3": "3",
    "q4": "4",
    "q5": "5",
    "q6": "6",
    "q7": "7",
    "q8": "8",
    "q9": "9",
    "q10": "10",
    "q11": "11",
    "q12": "12",
    "q13": "13"
  },
  "paragraphAnchors": {},
  "questionAnchors": {
    "q1": "q1-2-3-anchor",
    "q4": "q4-5-6-7-8-anchor",
    "q9": "q9-10-11-12-13-anchor",
    "q10": "q10_input",
    "q11": "q11_input",
    "q12": "q12_input",
    "q13": "q13_input",
    "q2": "q2_input",
    "q3": "q3_input",
    "q5": "q5",
    "q6": "q6",
    "q7": "q7",
    "q8": "q8"
  },
  "fields": {
    "choiceGroups": [
      {
        "name": "q1",
        "inputType": "radio",
        "questionIds": [
          "q1"
        ]
      },
      {
        "name": "q2",
        "inputType": "radio",
        "questionIds": [
          "q2"
        ]
      },
      {
        "name": "q3",
        "inputType": "radio",
        "questionIds": [
          "q3"
        ]
      }
    ],
    "textQuestions": [
      "q9",
      "q10",
      "q11",
      "q12",
      "q13"
    ],
    "selectQuestions": [],
    "textareaQuestions": [],
    "dropzoneQuestions": [
      "q4",
      "q5",
      "q6",
      "q7",
      "q8"
    ]
  },
  "totalQuestions": 13
}
